<?xml version='1.0'?>
<WwiseSettings>
    <CopySoundBanksAsPreBuildStep>true</CopySoundBanksAsPreBuildStep>
    <GenerateSoundBanksAsPreBuildStep>false</GenerateSoundBanksAsPreBuildStep>
    <SoundbankPath>Audio/GeneratedSoundBanks</SoundbankPath>
    <CreatedPicker>true</CreatedPicker>
    <CreateWwiseGlobal>true</CreateWwiseGlobal>
    <CreateWwiseListener>true</CreateWwiseListener>
    <ObjectReferenceAutoCleanup>true</ObjectReferenceAutoCleanup>
    <ShowMissingRigidBodyWarning>true</ShowMissingRigidBodyWarning>
    <ShowSpatialAudioWarningMsg>true</ShowSpatialAudioWarningMsg>
    <WwiseInstallationPathMac></WwiseInstallationPathMac>
    <WwiseInstallationPathWindows>E:\wwise\Wwise2021.1.14.8108</WwiseInstallationPathWindows>
    <WwiseProjectPath>E:/wwise/Projects/Space-Ship-Game/Space-Ship-Game.wproj</WwiseProjectPath>
    <UseWaapi>true</UseWaapi>
    <WaapiPort>8080</WaapiPort>
    <WaapiIP>127.0.0.1</WaapiIP>
</WwiseSettings>